NiukeQianduanGongchengshiQiuzhiJingyanFenxiang20212022/README.md
NiukeQianduanGongchengshiQiuzhiJingyanFenxiang20212022/__init__.py
NiukeQianduanGongchengshiQiuzhiJingyanFenxiang20212022/__main__.py
NiukeQianduanGongchengshiQiuzhiJingyanFenxiang20212022/file.epub
NiukeQianduanGongchengshiQiuzhiJingyanFenxiang20212022/index.html
NiukeQianduanGongchengshiQiuzhiJingyanFenxiang20212022/css/__init__.py
NiukeQianduanGongchengshiQiuzhiJingyanFenxiang20212022/css/annotations.css
NiukeQianduanGongchengshiQiuzhiJingyanFenxiang20212022/css/main.css
NiukeQianduanGongchengshiQiuzhiJingyanFenxiang20212022/css/normalize.css
NiukeQianduanGongchengshiQiuzhiJingyanFenxiang20212022/css/popup.css
NiukeQianduanGongchengshiQiuzhiJingyanFenxiang20212022/font/__init__.py
NiukeQianduanGongchengshiQiuzhiJingyanFenxiang20212022/font/fontello.eot
NiukeQianduanGongchengshiQiuzhiJingyanFenxiang20212022/font/fontello.svg
NiukeQianduanGongchengshiQiuzhiJingyanFenxiang20212022/font/fontello.ttf
NiukeQianduanGongchengshiQiuzhiJingyanFenxiang20212022/font/fontello.woff
NiukeQianduanGongchengshiQiuzhiJingyanFenxiang20212022/img/__init__.py
NiukeQianduanGongchengshiQiuzhiJingyanFenxiang20212022/img/annotator-glyph-sprite.png
NiukeQianduanGongchengshiQiuzhiJingyanFenxiang20212022/img/annotator-icon-sprite.png
NiukeQianduanGongchengshiQiuzhiJingyanFenxiang20212022/img/apple-touch-icon.png
NiukeQianduanGongchengshiQiuzhiJingyanFenxiang20212022/img/cancelfullscreen.png
NiukeQianduanGongchengshiQiuzhiJingyanFenxiang20212022/img/close.png
NiukeQianduanGongchengshiQiuzhiJingyanFenxiang20212022/img/fullscreen.png
NiukeQianduanGongchengshiQiuzhiJingyanFenxiang20212022/img/loader.gif
NiukeQianduanGongchengshiQiuzhiJingyanFenxiang20212022/img/menu-icon.png
NiukeQianduanGongchengshiQiuzhiJingyanFenxiang20212022/img/save.png
NiukeQianduanGongchengshiQiuzhiJingyanFenxiang20212022/img/saved.png
NiukeQianduanGongchengshiQiuzhiJingyanFenxiang20212022/img/settings-s.png
niuke_qianduan_gongchengshi_qiuzhi_jingyan_fenxiang_2021_2022-2024.3.6.0.dist-info/METADATA
niuke_qianduan_gongchengshi_qiuzhi_jingyan_fenxiang_2021_2022-2024.3.6.0.dist-info/WHEEL
niuke_qianduan_gongchengshi_qiuzhi_jingyan_fenxiang_2021_2022-2024.3.6.0.dist-info/entry_points.txt
niuke_qianduan_gongchengshi_qiuzhi_jingyan_fenxiang_2021_2022-2024.3.6.0.dist-info/top_level.txt
niuke_qianduan_gongchengshi_qiuzhi_jingyan_fenxiang_2021_2022-2024.3.6.0.dist-info/RECORD
